weather/server.py
chst_weather-0.1.2.dist-info/METADATA
chst_weather-0.1.2.dist-info/WHEEL
chst_weather-0.1.2.dist-info/entry_points.txt
chst_weather-0.1.2.dist-info/RECORD
