Metadata-Version: 2.4
Name: chst-weather
Version: 0.1.2
Summary: A simple MCP weather server
Requires-Python: >=3.10
Requires-Dist: httpx>=0.28.1
Requires-Dist: mcp[cli]>=1.21.0
